simply_useful/__init__.py
simply_useful/simply_useful.py
simply_useful-1.0.0.dist-info/LICENSE
simply_useful-1.0.0.dist-info/METADATA
simply_useful-1.0.0.dist-info/WHEEL
simply_useful-1.0.0.dist-info/top_level.txt
simply_useful-1.0.0.dist-info/RECORD
