Metadata-Version: 2.1
Name: simply_useful
Version: 1.0.0
Summary: A collection of reusable utility functions, classes, and decorators.
Author-email: Dayton Jones <jones.dayton@gmail.com>
Maintainer-email: Dayton Jones <jones.dayton@gmail.com>
Project-URL: Homepage, https://github.com/daytonjones/DevPotluck/tree/main/python/SimplyUseful
Project-URL: Issues, https://github.com/daytonjones/DevPotluck/issues
Keywords: utility,reusable
Classifier: Programming Language :: Python :: 3
Classifier: License :: OSI Approved :: MIT License
Classifier: Operating System :: OS Independent
Requires-Python: >=3.8
License-File: LICENSE
